[
  {
    "question": "宮崎駿氏が受賞した賞の名前は何ですか？",
    "options": [
      "アジアの平和賞",
      "マグサイサイ賞",
      "スタジオジブリ賞",
      "アニメーション大賞"
    ],
    "answer": 1,
    "explanation": "宮崎駿氏が受賞したのは「マグサイサイ賞」であり、これはアジア地域での平和や社会の発展に尽くした個人や団体をたたえる賞です。"
  },
  {
    "question": "宮崎駿氏が制作した作品の特徴は何ですか？",
    "options": [
      "複雑な問題を子どもにも理解できるように表現している",
      "全ての作品が実写映画である",
      "作品は全て短編アニメである",
      "社会問題を扱わないエンターテイメント作品である"
    ],
    "answer": 0,
    "explanation": "宮崎駿氏の作品は、環境保全や平和、ジェンダー平等などの社会の課題を扱い、子どもにも理解できるように表現されています。"
  },
  {
    "question": "マグサイサイ賞はいつ設立されましたか？",
    "options": [
      "1957年",
      "1965年",
      "1972年",
      "1980年"
    ],
    "answer": 0,
    "explanation": "マグサイサイ賞は1957年に設立され、フィリピンの故マグサイサイ大統領を記念した賞です。"
  },
  {
    "question": "宮崎駿氏が受賞した年は何年ですか？",
    "options": [
      "2022年",
      "2023年",
      "2024年",
      "2025年"
    ],
    "answer": 2,
    "explanation": "宮崎駿氏が受賞したのは2024年のマグサイサイ賞です。"
  },
  {
    "question": "マグサイサイ賞の受賞者として過去に日本人は誰が選ばれていますか？",
    "options": [
      "中村哲医師",
      "宮崎駿氏",
      "村上春樹",
      "黒澤明"
    ],
    "answer": 0,
    "explanation": "過去にマグサイサイ賞を受賞した日本人には、中村哲医師が含まれています。"
  }
]