[
  {
    "question": "台風15号はどの地域で発生したと発表されましたか？",
    "options": [
      "鹿児島県奄美大島の東",
      "宮崎県の南",
      "東京都の西",
      "四国の北"
    ],
    "answer": 0,
    "explanation": "台風15号は鹿児島県奄美大島の東で発生したと気象庁が発表しました。"
  },
  {
    "question": "台風15号の中心の気圧は何ヘクトパスカルですか？",
    "options": [
      "950ヘクトパスカル",
      "1000ヘクトパスカル",
      "1020ヘクトパスカル",
      "980ヘクトパスカル"
    ],
    "answer": 1,
    "explanation": "台風15号の中心の気圧は1000ヘクトパスカルです。"
  },
  {
    "question": "台風15号はどの方向に進んでいますか？",
    "options": [
      "南へ",
      "北へ",
      "西へ",
      "東へ"
    ],
    "answer": 1,
    "explanation": "台風15号は時速25キロの速さで北へ進んでいます。"
  },
  {
    "question": "線状降水帯が発生する可能性がある県はどれですか？",
    "options": [
      "北海道",
      "宮崎県",
      "沖縄県",
      "山梨県"
    ],
    "answer": 1,
    "explanation": "線状降水帯は宮崎県で4日夜遅くに発生する可能性があります。"
  },
  {
    "question": "5日午後6時までの24時間降水量の予想で、最も多い地域はどこですか？",
    "options": [
      "関東甲信",
      "近畿",
      "東海",
      "九州北部"
    ],
    "answer": 2,
    "explanation": "5日午後6時までの24時間降水量は東海が300ミリと予想されています。"
  }
]