[
  {
    "question": "この記事で政府が22日に閣議決定したものは何ですか？",
    "options": [
      "少子化社会対策大綱",
      "こども基本法",
      "こども大綱",
      "子どもらからの意見"
    ],
    "answer": 2,
    "explanation": "記事で述べられているのは政府が22日に初の「こども大綱」を閣議決定したことです。"
  },
  {
    "question": "大綱に盛り込まれた数値目標は何ですか？",
    "options": [
      "20・3%",
      "70%",
      "5年後",
      "2023年"
    ],
    "answer": 1,
    "explanation": "大綱には、5年後までに「政策に関して意見を聴いてもらえている」と思う子ども・若者の割合を20・3%（2023年）から70%に引き上げる数値目標も盛り込まれています。"
  },
  {
    "question": "大綱で定められた基本方針の数は何ですか？",
    "options": [
      "4つ",
      "6つ",
      "8つ",
      "10つ"
    ],
    "answer": 1,
    "explanation": "大綱では、子どもや若者の「最善の利益を図る」といった六つの基本方針を定めています。"
  },
  {
    "question": "大綱で新設された項目は何ですか？",
    "options": [
      "校則の見直し",
      "いじめ防止",
      "体罰の根絶",
      "政策に関して意見を聴く"
    ],
    "answer": 0,
    "explanation": "大綱には、1日にまとめた答申に「校則の見直し」の項目を新設することが盛り込まれています。"
  },
  {
    "question": "この記事で述べられている大綱の策定の背景は何ですか？",
    "options": [
      "こども基本法",
      "少子化社会対策大綱",
      "子ども政策の方向性",
      "従来の3大綱"
    ],
    "answer": 1,
    "explanation": "こども基本法に基づく大綱は「少子化社会対策大綱」など従来の3大綱を一本化して策定されたという背景が記事で述べられています。"
  }
]