[
  {
    "question": "新庄博志さんの遺体が見つかった場所はどこですか？",
    "options": [
      "大津市仰木の里4丁目",
      "大津市仰木の里東6丁目",
      "大津市内の路上",
      "新庄さん宅"
    ],
    "answer": 1,
    "explanation": "遺体が見つかった場所は大津市仰木の里東6丁目の民家です。"
  },
  {
    "question": "飯塚容疑者は何を持っていたとして銃刀法違反の疑いで逮捕された？",
    "options": [
      "包丁",
      "ナイフ",
      "鉄パイプ",
      "ハンマー"
    ],
    "answer": 1,
    "explanation": "飯塚容疑者は刃体6センチを超えるナイフを持っていたとして逮捕されました。"
  },
  {
    "question": "新庄博志さんの死因は何でしたか？",
    "options": [
      "窒息",
      "心臓発作",
      "出血性ショック",
      "中毒"
    ],
    "answer": 2,
    "explanation": "新庄博志さんの死因は出血性ショックでした。"
  },
  {
    "question": "飯塚容疑者は新庄博志さんと面会する予定だった日時はいつですか？",
    "options": [
      "5月24日午後7時",
      "5月26日午後4時",
      "5月28日深夜",
      "5月24日夜"
    ],
    "answer": 0,
    "explanation": "飯塚容疑者は新庄博志さんと面会する予定だった日時は5月24日午後7時です。"
  },
  {
    "question": "飯塚容疑者は事件に関して何と主張していますか？",
    "options": [
      "犯行を認めた",
      "無実を主張",
      "記憶がない",
      "他の犯人がいる"
    ],
    "answer": 1,
    "explanation": "飯塚容疑者は容疑を否認しており、無実を主張しています。"
  }
]