[
  {
    "question": "この記事で予想されている降雪量が最も多い地域はどこですか？",
    "options": [
      "群馬県",
      "東京都",
      "静岡県",
      "神奈川県"
    ],
    "answer": 0,
    "explanation": "群馬県では警報級の大雪が予想されており、特に降雪量が多いとされています。"
  },
  {
    "question": "交通機関に影響を与える原因は何ですか？",
    "options": [
      "低気圧の通過",
      "地震の発生",
      "台風の接近",
      "火山の噴火"
    ],
    "answer": 0,
    "explanation": "前線を伴う低気圧が本州南岸を通過する影響で、交通機関に影響が出ています。"
  },
  {
    "question": "国土交通省が実施した通行止めはいつから始まりましたか？",
    "options": [
      "3日朝から",
      "4日午後から",
      "5日正午から",
      "2日夕方から"
    ],
    "answer": 0,
    "explanation": "国土交通省関東地方整備局は3日朝から通行止めを実施しました。"
  },
  {
    "question": "JR東日本が運転を取りやめる特急はどれですか？",
    "options": [
      "特急あずさ",
      "特急かいじ",
      "特急富士回遊",
      "特急ひかり"
    ],
    "answer": 0,
    "explanation": "JR東日本は特急あずさの運転を取りやめると発表しています。"
  },
  {
    "question": "担当者が呼びかけていることは何ですか？",
    "options": [
      "外出を控えること",
      "旅行を推奨すること",
      "学校を休校にすること",
      "イベントを開催すること"
    ],
    "answer": 0,
    "explanation": "担当者は外出を控えるための予定の変更やテレワークの活用を検討してほしいと呼びかけています。"
  }
]