[
  {
    "question": "東かがわ国際芸術祭に関する問題で、出品者からの主な不満は何ですか？",
    "options": [
      "作品が返却されないこと",
      "作品の展示が予定より早く終わったこと",
      "作品の展示場所が変更されたこと",
      "出品者への連絡が遅れたこと"
    ],
    "answer": 0,
    "explanation": "出品者からは「作品が返却されない」という不満が寄せられており、これは記事の中で明確に述べられています。"
  },
  {
    "question": "東かがわ市が19日に発表した内容は何ですか？",
    "options": [
      "イベントを企画した団体に活動実態がないことが判明した",
      "出品者からの相談が多かったこと",
      "県との連携が進んでいること",
      "イベントの後援を行うことを決定した"
    ],
    "answer": 0,
    "explanation": "東かがわ市は、イベントを企画した団体に活動実態がないことが判明したと発表しています。"
  },
  {
    "question": "県警東かがわ署はどのような相談を受けていますか？",
    "options": [
      "出品者からの相談",
      "観客からの苦情",
      "イベントの開催許可に関する相談",
      "資金援助に関する問い合わせ"
    ],
    "answer": 0,
    "explanation": "県警東かがわ署は、出品者からの相談を受けていると記事に記載されています。"
  },
  {
    "question": "東かがわ国際芸術祭のサイトにはどのような記載がありますか？",
    "options": [
      "県や東かがわ市が協力団体として記載されている",
      "出品者の作品が全て掲載されている",
      "イベントの詳細なスケジュールが記載されている",
      "参加アーティストのプロフィールが掲載されている"
    ],
    "answer": 0,
    "explanation": "サイトには県や東かがわ市が協力団体として記載されていますが、両自治体はそれを否定しています。"
  },
  {
    "question": "上村一郎市長はどのような感想を述べていますか？",
    "options": [
      "作家からの相談に困惑している",
      "イベントの成功を期待している",
      "県との連携を強化する必要がある",
      "出品者に対して謝罪するべきだ"
    ],
    "answer": 0,
    "explanation": "上村一郎市長は、作家から「被害を受けている」との相談が寄せられており、困惑していると述べています。"
  }
]